home_bank_converter
