Metadata-Version: 1.0
Name: home-bank-converter
Version: 0.1.1
Summary: Converter for various online banking transaction files to be able to import them to HomeBank (http://homebank.free.fr)
Home-page: https://github.com/FabianReister/home_bank_converter
Author: Fabian Reister
Author-email: UNKNOWN
License: GPL-3.0
Platform: UNKNOWN
